example_pkg/__init__.py
seleniumbase_runping.zeng-0.1.6.dist-info/LICENSE
seleniumbase_runping.zeng-0.1.6.dist-info/METADATA
seleniumbase_runping.zeng-0.1.6.dist-info/WHEEL
seleniumbase_runping.zeng-0.1.6.dist-info/top_level.txt
seleniumbase_runping.zeng-0.1.6.dist-info/RECORD
